Metadata-Version: 2.1
Name: textx-model
Version: 0.0.5
Summary: Meta-language for DSL implementation inspired by Xtext
Home-page: https://gitee.com/maxbanana
Author: hongbo liu
Author-email: 782027465@qq.com
License: Apache
Platform: UNKNOWN
Classifier: Programming Language :: Python :: 3
Classifier: License :: OSI Approved :: Apache Software License
Classifier: Operating System :: OS Independent
Requires-Python: >=3.8.5
License-File: LICENSE
